pyfolding/__init__.py
pyfolding/batch.py
pyfolding/libfolding.py
pyfolding/pvalues.py
pyfolding/results.py
pyfolding/stream.py
pyfolding-1.1.1.dist-info/LICENSE
pyfolding-1.1.1.dist-info/METADATA
pyfolding-1.1.1.dist-info/WHEEL
pyfolding-1.1.1.dist-info/top_level.txt
pyfolding-1.1.1.dist-info/RECORD
