Metadata-Version: 2.1
Name: pyfolding
Version: 1.1.1
Summary: Python3 bindings to libfolding
Home-page: https://github.com/asiffer/python3-libfolding
Author: Alban Siffer
Author-email: alban.siffer@irisa.fr
License: GPL-3
Platform: UNKNOWN
